roman-numeral/__init__.py
roman-numeral/roman_numeral1.py
roman_numeral/__init__.py
roman_numeral/roman_numeral.py
romanlibrary/__init__.py
romanlibrary/romanlibrary.py
romanlibrary-1.3.1.dist-info/METADATA
romanlibrary-1.3.1.dist-info/WHEEL
romanlibrary-1.3.1.dist-info/top_level.txt
romanlibrary-1.3.1.dist-info/RECORD
