Metadata-Version: 2.1
Name: romanlibrary
Version: 1.3.1
Summary: A Python library for drawing Roman numerals using Turtle graphics
Home-page: https://github.com/nicestuff77/roman-numeral
Author: Cort Smith
Author-email: cort.j.smith@gmail.com
Keywords: roman numeral turtle graphics drawing
Classifier: Programming Language :: Python :: 3
Classifier: License :: OSI Approved :: MIT License
Classifier: Operating System :: OS Independent
